{
  "name": "SOD-123FL",
  "type": "Chip",
  "body": {
    "length": 3.7,
    "width": 1.7
  },
  "chip": {
    "chipLength": 3.7,
    "leadWidth": 1.7,
    "leadLength": 0.3
  },
  "aliases": [
    "SOD123FL"
  ],
  "height": {
    "nominal": 0.95,
    "max": 1.15,
    "min": 0.75
  },
  "searchArea": {
    "x": 3.6,
    "y": 1.65
  },
  "machine": {
    "mountTools": [
      "A13"
    ],
    "hydraTools": [
      "H04"
    ],
    "pickWaitTime": 50,
    "placeWaitTime": 50,
    "zMountForce": 3500,
    "flags": {
      "pickPositionFeedback": false,
      "holdDuringXMove": false,
      "vacuumTest": false
    },
    "accelerations": {
      "x": "highest",
      "y": "highest",
      "tape": "highest",
      "theta": "highest",
      "z": "highest",
      "hydraTheta": "highest",
      "hydraZ": "highest"
    },
    "centering": [
      {
        "method": "optical",
        "tools": [
          "Z_TOOL"
        ]
      }
    ],
    "visionModes": [
      "linescan"
    ],
    "coplanarityCheck": false
  }
}
