{
  "name": "QFN-12-1EP_3X3MM_P0.51MM_EP1.45X1",
  "type": "PT_FOUR_SYM",
  "body": {
    "length": 3,
    "width": 3
  },
  "fourSymmetric": {
    "numberOfLeads": 12,
    "widthOverLeads": 3.75,
    "leadPitch": 0.51,
    "leadWidth": 0.3,
    "leadLength": 0.875
  },
  "aliases": [],
  "provenance": {
    "owner": "newmatik",
    "sourceLibrary": "kicad-footprints",
    "sourceType": "KiCad",
    "sourceFile": ".local/libraries/cc-by-sa-4.0-kicad-exception/KiCad/kicad-footprints/Package_DFN_QFN.pretty/QFN-12-1EP_3x3mm_P0.51mm_EP1.45x1.45mm.kicad_mod",
    "sourceFootprint": "QFN-12-1EP_3x3mm_P0.51mm_EP1.45x1.45mm"
  }
}
